storylines/__init__.py
storylines/calc.py
storylines/color.py
storylines/convert.py
storylines/cut.py
storylines/fatband.py
storylines/files.py
storylines/group.py
storylines/plot.py
storylines/png.py
storylines/proj.py
storylines-0.16.dist-info/licenses/LICENSE
storylines-0.16.dist-info/WHEEL
storylines-0.16.dist-info/METADATA
storylines-0.16.dist-info/RECORD
