Metadata-Version: 2.4
Name: storylines
Version: 0.16
Summary: Line plots with Python & TikZ
Author: Jan Berges
Requires-Python: >=2.7
Classifier: License :: OSI Approved :: Zero-Clause BSD (0BSD)
Classifier: Programming Language :: Python
License-File: LICENSE
Project-URL: Homepage, https://github.com/janberges/StoryLines
